LICENSE
MANIFEST.in
README.rst
setup.py
django_smsaero.egg-info/PKG-INFO
django_smsaero.egg-info/SOURCES.txt
django_smsaero.egg-info/dependency_links.txt
django_smsaero.egg-info/requires.txt
django_smsaero.egg-info/top_level.txt
smsaero/__init__.py
smsaero/admin.py
smsaero/conf.py
smsaero/factories.py
smsaero/models.py
smsaero/tests.py
smsaero/urls.py
smsaero/utils.py