Metadata-Version: 1.0
Name: django-smsaero
Version: 0.9.4
Summary: A simple Django app for send SMS via smsaero.ru.
Home-page: http://github.com/drmartiner/django-smsaero/
Author: DrMartiner
Author-email: DrMartiner@GMail.Com
License: MIT
Platform: UNKNOWN
Classifier: Environment :: Web Environment
Classifier: Framework :: Django
Classifier: Intended Audience :: Developers
Classifier: License :: OSI Approved :: MIT License
Classifier: Operating System :: OS Independent
Classifier: Programming Language :: Python
Classifier: Programming Language :: Python :: 2.6
Classifier: Programming Language :: Python :: 2.7
Classifier: Topic :: Internet :: WWW/HTTP
Classifier: Topic :: Internet :: WWW/HTTP :: Dynamic Content
